{
"scenario_name": "Compute Unit Count vs. Performance",
"plugin_name": "Matrix Multiply",
"label": "39",
"release_time": 0.000000,
"compute_unit_count": 60,
"threads_per_compute_unit": 2560,
"clock_rate": 18446744073709509924,
"warp_size": 64,
"starting_clock": 14752990207579,
"PID": 5375,
"TID": 5380,
"times": [{},
{"copy_in_times": [0.461689363,0.461714251], "execute_times": [0.461714294,0.466486902], "copy_out_times": [0.466486942,0.466528265], "cpu_times": [0.461689363,0.466528265], "cpu_core": 1},
{"kernel_name": "matrix_multiply", "block_count": 1024, "thread_count": 1024, "shared_memory": 0, "kernel_launch_times": [0.461714347, 0.461717887, 0.466486827], "block_times": []},
{"copy_in_times": [0.466543503,0.466575028], "execute_times": [0.466575068,0.471368097], "copy_out_times": [0.471368150,0.471411726], "cpu_times": [0.466543503,0.471411726], "cpu_core": 1},
{"kernel_name": "matrix_multiply", "block_count": 1024, "thread_count": 1024, "shared_memory": 0, "kernel_launch_times": [0.466575109, 0.466578811, 0.471368020], "block_times": []},
{"copy_in_times": [0.471421657,0.471447208], "execute_times": [0.471447244,0.476230983], "copy_out_times": [0.476231045,0.476274195], "cpu_times": [0.471421657,0.476274195], "cpu_core": 1},
{"kernel_name": "matrix_multiply", "block_count": 1024, "thread_count": 1024, "shared_memory": 0, "kernel_launch_times": [0.471447288, 0.471450535, 0.476230902], "block_times": []},
{"copy_in_times": [0.476282962,0.476307871], "execute_times": [0.476307908,0.481069589], "copy_out_times": [0.481069646,0.481112649], "cpu_times": [0.476282962,0.481112649], "cpu_core": 1},
{"kernel_name": "matrix_multiply", "block_count": 1024, "thread_count": 1024, "shared_memory": 0, "kernel_launch_times": [0.476307946, 0.476311322, 0.481069517], "block_times": []},
{"copy_in_times": [0.481120883,0.481145125], "execute_times": [0.481145164,0.485911670], "copy_out_times": [0.485911727,0.485954287], "cpu_times": [0.481120883,0.485954287], "cpu_core": 1},
{"kernel_name": "matrix_multiply", "block_count": 1024, "thread_count": 1024, "shared_memory": 0, "kernel_launch_times": [0.481145201, 0.481148032, 0.485911605], "block_times": []},
{"copy_in_times": [0.485963032,0.485988135], "execute_times": [0.485988173,0.490721203], "copy_out_times": [0.490721260,0.490764607], "cpu_times": [0.485963032,0.490764607], "cpu_core": 1},
{"kernel_name": "matrix_multiply", "block_count": 1024, "thread_count": 1024, "shared_memory": 0, "kernel_launch_times": [0.485988210, 0.485991451, 0.490721135], "block_times": []},
{"copy_in_times": [0.490772829,0.490797423], "execute_times": [0.490797460,0.495544035], "copy_out_times": [0.495544101,0.495587219], "cpu_times": [0.490772829,0.495587219], "cpu_core": 1},
{"kernel_name": "matrix_multiply", "block_count": 1024, "thread_count": 1024, "shared_memory": 0, "kernel_launch_times": [0.490797498, 0.490800629, 0.495543951], "block_times": []},
{"copy_in_times": [0.495596045,0.495621428], "execute_times": [0.495621465,0.500393524], "copy_out_times": [0.500393579,0.500437298], "cpu_times": [0.495596045,0.500437298], "cpu_core": 1},
{"kernel_name": "matrix_multiply", "block_count": 1024, "thread_count": 1024, "shared_memory": 0, "kernel_launch_times": [0.495621504, 0.495625015, 0.500393454], "block_times": []},
{"copy_in_times": [0.500445454,0.500470592], "execute_times": [0.500470629,0.505240925], "copy_out_times": [0.505240985,0.505283827], "cpu_times": [0.500445454,0.505283827], "cpu_core": 1},
{"kernel_name": "matrix_multiply", "block_count": 1024, "thread_count": 1024, "shared_memory": 0, "kernel_launch_times": [0.500470667, 0.500473425, 0.505240858], "block_times": []},
{"copy_in_times": [0.505292982,0.505341937], "execute_times": [0.505341978,0.510105133], "copy_out_times": [0.510105193,0.510149344], "cpu_times": [0.505292982,0.510149344], "cpu_core": 1},
{"kernel_name": "matrix_multiply", "block_count": 1024, "thread_count": 1024, "shared_memory": 0, "kernel_launch_times": [0.505342017, 0.505345438, 0.510105085], "block_times": []},
{"copy_in_times": [0.510157710,0.510183326], "execute_times": [0.510183362,0.514945471], "copy_out_times": [0.514945535,0.514988006], "cpu_times": [0.510157710,0.514988006], "cpu_core": 1},
{"kernel_name": "matrix_multiply", "block_count": 1024, "thread_count": 1024, "shared_memory": 0, "kernel_launch_times": [0.510183401, 0.510186450, 0.514945411], "block_times": []},
{"copy_in_times": [0.515004508,0.515037568], "execute_times": [0.515037606,0.519822361], "copy_out_times": [0.519822404,0.519869353], "cpu_times": [0.515004508,0.519869353], "cpu_core": 1},
{"kernel_name": "matrix_multiply", "block_count": 1024, "thread_count": 1024, "shared_memory": 0, "kernel_launch_times": [0.515037654, 0.515041201, 0.519822294], "block_times": []},
{"copy_in_times": [0.519878260,0.519902969], "execute_times": [0.519903007,0.524702566], "copy_out_times": [0.524702626,0.524747328], "cpu_times": [0.519878260,0.524747328], "cpu_core": 1},
{"kernel_name": "matrix_multiply", "block_count": 1024, "thread_count": 1024, "shared_memory": 0, "kernel_launch_times": [0.519903045, 0.519906256, 0.524702506], "block_times": []},
{"copy_in_times": [0.524755685,0.524780875], "execute_times": [0.524780914,0.529547009], "copy_out_times": [0.529547070,0.529589575], "cpu_times": [0.524755685,0.529589575], "cpu_core": 1},
{"kernel_name": "matrix_multiply", "block_count": 1024, "thread_count": 1024, "shared_memory": 0, "kernel_launch_times": [0.524780950, 0.524784201, 0.529546925], "block_times": []},
{"copy_in_times": [0.529598736,0.529623953], "execute_times": [0.529623992,0.534400277], "copy_out_times": [0.534400337,0.534442962], "cpu_times": [0.529598736,0.534442962], "cpu_core": 1},
{"kernel_name": "matrix_multiply", "block_count": 1024, "thread_count": 1024, "shared_memory": 0, "kernel_launch_times": [0.529624028, 0.529627414, 0.534400222], "block_times": []},
{"copy_in_times": [0.534451617,0.534477084], "execute_times": [0.534477123,0.539224671], "copy_out_times": [0.539224733,0.539267302], "cpu_times": [0.534451617,0.539267302], "cpu_core": 1},
{"kernel_name": "matrix_multiply", "block_count": 1024, "thread_count": 1024, "shared_memory": 0, "kernel_launch_times": [0.534477168, 0.534480510, 0.539224606], "block_times": []},
{"copy_in_times": [0.539275948,0.539301404], "execute_times": [0.539301442,0.544071962], "copy_out_times": [0.544071998,0.544116052], "cpu_times": [0.539275948,0.544116052], "cpu_core": 1},
{"kernel_name": "matrix_multiply", "block_count": 1024, "thread_count": 1024, "shared_memory": 0, "kernel_launch_times": [0.539301492, 0.539304875, 0.544071899], "block_times": []},
{"copy_in_times": [0.544122869,0.544148714], "execute_times": [0.544148743,0.548930884], "copy_out_times": [0.548930941,0.548973426], "cpu_times": [0.544122869,0.548973426], "cpu_core": 1},
{"kernel_name": "matrix_multiply", "block_count": 1024, "thread_count": 1024, "shared_memory": 0, "kernel_launch_times": [0.544148774, 0.544151721, 0.548930820], "block_times": []},
{"copy_in_times": [0.548980198,0.549005340], "execute_times": [0.549005369,0.553774608], "copy_out_times": [0.553774641,0.553831156], "cpu_times": [0.548980198,0.553831156], "cpu_core": 1},
{"kernel_name": "matrix_multiply", "block_count": 1024, "thread_count": 1024, "shared_memory": 0, "kernel_launch_times": [0.549005400, 0.549008042, 0.553774541], "block_times": []},
{"copy_in_times": [0.553838359,0.553863950], "execute_times": [0.553863979,0.558669996], "copy_out_times": [0.558670029,0.558717805], "cpu_times": [0.553838359,0.558717805], "cpu_core": 1},
{"kernel_name": "matrix_multiply", "block_count": 1024, "thread_count": 1024, "shared_memory": 0, "kernel_launch_times": [0.553864010, 0.553867074, 0.558669928], "block_times": []},
{"copy_in_times": [0.558724414,0.558751197], "execute_times": [0.558751227,0.563578900], "copy_out_times": [0.563578935,0.563622008], "cpu_times": [0.558724414,0.563622008], "cpu_core": 1},
{"kernel_name": "matrix_multiply", "block_count": 1024, "thread_count": 1024, "shared_memory": 0, "kernel_launch_times": [0.558751258, 0.558753914, 0.563578832], "block_times": []},
{"copy_in_times": [0.563629414,0.563654290], "execute_times": [0.563654321,0.568415791], "copy_out_times": [0.568415830,0.568460557], "cpu_times": [0.563629414,0.568460557], "cpu_core": 1},
{"kernel_name": "matrix_multiply", "block_count": 1024, "thread_count": 1024, "shared_memory": 0, "kernel_launch_times": [0.563654350, 0.563657308, 0.568415726], "block_times": []},
{"copy_in_times": [0.568471884,0.568496613], "execute_times": [0.568496643,0.573263833], "copy_out_times": [0.573263885,0.573323999], "cpu_times": [0.568471884,0.573323999], "cpu_core": 1},
{"kernel_name": "matrix_multiply", "block_count": 1024, "thread_count": 1024, "shared_memory": 0, "kernel_launch_times": [0.568496683, 0.568499788, 0.573263769], "block_times": []},
{"copy_in_times": [0.573331991,0.573358830], "execute_times": [0.573358858,0.578113576], "copy_out_times": [0.578113626,0.578155913], "cpu_times": [0.573331991,0.578155913], "cpu_core": 1},
{"kernel_name": "matrix_multiply", "block_count": 1024, "thread_count": 1024, "shared_memory": 0, "kernel_launch_times": [0.573358898, 0.573362034, 0.578113512], "block_times": []},
{"copy_in_times": [0.578162699,0.578187851], "execute_times": [0.578187882,0.582964258], "copy_out_times": [0.582964308,0.583005366], "cpu_times": [0.578162699,0.583005366], "cpu_core": 1},
{"kernel_name": "matrix_multiply", "block_count": 1024, "thread_count": 1024, "shared_memory": 0, "kernel_launch_times": [0.578187912, 0.578190676, 0.582964195], "block_times": []},
{"copy_in_times": [0.583012088,0.583036716], "execute_times": [0.583036746,0.587781637], "copy_out_times": [0.587781687,0.587830329], "cpu_times": [0.583012088,0.587830329], "cpu_core": 1},
{"kernel_name": "matrix_multiply", "block_count": 1024, "thread_count": 1024, "shared_memory": 0, "kernel_launch_times": [0.583036778, 0.583039473, 0.587781566], "block_times": []},
{"copy_in_times": [0.587837405,0.587863335], "execute_times": [0.587863368,0.592636765], "copy_out_times": [0.592636820,0.592679668], "cpu_times": [0.587837405,0.592679668], "cpu_core": 1},
{"kernel_name": "matrix_multiply", "block_count": 1024, "thread_count": 1024, "shared_memory": 0, "kernel_launch_times": [0.587863397, 0.587866082, 0.592636700], "block_times": []},
{"copy_in_times": [0.592686460,0.592710513], "execute_times": [0.592710544,0.597436560], "copy_out_times": [0.597436610,0.597481295], "cpu_times": [0.592686460,0.597481295], "cpu_core": 1},
{"kernel_name": "matrix_multiply", "block_count": 1024, "thread_count": 1024, "shared_memory": 0, "kernel_launch_times": [0.592710574, 0.592713445, 0.597436482], "block_times": []},
{"copy_in_times": [0.597488552,0.597513441], "execute_times": [0.597513477,0.602278454], "copy_out_times": [0.602278489,0.602323136], "cpu_times": [0.597488552,0.602323136], "cpu_core": 1},
{"kernel_name": "matrix_multiply", "block_count": 1024, "thread_count": 1024, "shared_memory": 0, "kernel_launch_times": [0.597513509, 0.597516103, 0.602278391], "block_times": []},
{"copy_in_times": [0.602329924,0.602357067], "execute_times": [0.602357097,0.607111818], "copy_out_times": [0.607111867,0.607153232], "cpu_times": [0.602329924,0.607153232], "cpu_core": 1},
{"kernel_name": "matrix_multiply", "block_count": 1024, "thread_count": 1024, "shared_memory": 0, "kernel_launch_times": [0.602357127, 0.602359833, 0.607111740], "block_times": []},
{"copy_in_times": [0.607160456,0.607185040], "execute_times": [0.607185070,0.611972679], "copy_out_times": [0.611972728,0.612016086], "cpu_times": [0.607160456,0.612016086], "cpu_core": 1},
{"kernel_name": "matrix_multiply", "block_count": 1024, "thread_count": 1024, "shared_memory": 0, "kernel_launch_times": [0.607185100, 0.607187855, 0.611972616], "block_times": []},
{"copy_in_times": [0.612022901,0.612055525], "execute_times": [0.612055556,0.616810995], "copy_out_times": [0.616811049,0.616854697], "cpu_times": [0.612022901,0.616854697], "cpu_core": 1},
{"kernel_name": "matrix_multiply", "block_count": 1024, "thread_count": 1024, "shared_memory": 0, "kernel_launch_times": [0.612055586, 0.612058199, 0.616810904], "block_times": []},
{"copy_in_times": [0.616864262,0.616888662], "execute_times": [0.616888692,0.621640280], "copy_out_times": [0.621640335,0.621682630], "cpu_times": [0.616864262,0.621682630], "cpu_core": 1},
{"kernel_name": "matrix_multiply", "block_count": 1024, "thread_count": 1024, "shared_memory": 0, "kernel_launch_times": [0.616888741, 0.616891908, 0.621640204], "block_times": []},
{"copy_in_times": [0.621694593,0.621719337], "execute_times": [0.621719367,0.626434945], "copy_out_times": [0.626434995,0.626477343], "cpu_times": [0.621694593,0.626477343], "cpu_core": 1},
{"kernel_name": "matrix_multiply", "block_count": 1024, "thread_count": 1024, "shared_memory": 0, "kernel_launch_times": [0.621719413, 0.621722308, 0.626434883], "block_times": []},
{"copy_in_times": [0.626484496,0.626508544], "execute_times": [0.626508573,0.631251496], "copy_out_times": [0.631251544,0.631293319], "cpu_times": [0.626484496,0.631293319], "cpu_core": 1},
{"kernel_name": "matrix_multiply", "block_count": 1024, "thread_count": 1024, "shared_memory": 0, "kernel_launch_times": [0.626508618, 0.626511275, 0.631251428], "block_times": []},
{"copy_in_times": [0.631300514,0.631324557], "execute_times": [0.631324589,0.636078740], "copy_out_times": [0.636078788,0.636121817], "cpu_times": [0.631300514,0.636121817], "cpu_core": 1},
{"kernel_name": "matrix_multiply", "block_count": 1024, "thread_count": 1024, "shared_memory": 0, "kernel_launch_times": [0.631324625, 0.631327335, 0.636078686], "block_times": []},
{"copy_in_times": [0.636128573,0.636153569], "execute_times": [0.636153601,0.640921951], "copy_out_times": [0.640921996,0.640966938], "cpu_times": [0.636128573,0.640966938], "cpu_core": 1},
{"kernel_name": "matrix_multiply", "block_count": 1024, "thread_count": 1024, "shared_memory": 0, "kernel_launch_times": [0.636153632, 0.636156174, 0.640921886], "block_times": []},
{"copy_in_times": [0.640974014,0.640999497], "execute_times": [0.640999529,0.645754258], "copy_out_times": [0.645754306,0.645828991], "cpu_times": [0.640974014,0.645828991], "cpu_core": 1},
{"kernel_name": "matrix_multiply", "block_count": 1024, "thread_count": 1024, "shared_memory": 0, "kernel_launch_times": [0.640999558, 0.641002373, 0.645754207], "block_times": []},
{"copy_in_times": [0.645835822,0.645860426], "execute_times": [0.645860457,0.650635129], "copy_out_times": [0.650635176,0.650677521], "cpu_times": [0.645835822,0.650677521], "cpu_core": 1},
{"kernel_name": "matrix_multiply", "block_count": 1024, "thread_count": 1024, "shared_memory": 0, "kernel_launch_times": [0.645860487, 0.645863374, 0.650635064], "block_times": []},
{"copy_in_times": [0.650684767,0.650709712], "execute_times": [0.650709744,0.655473877], "copy_out_times": [0.655473926,0.655515645], "cpu_times": [0.650684767,0.655515645], "cpu_core": 1},
{"kernel_name": "matrix_multiply", "block_count": 1024, "thread_count": 1024, "shared_memory": 0, "kernel_launch_times": [0.650709775, 0.650712842, 0.655473814], "block_times": []},
{"copy_in_times": [0.655522388,0.655547313], "execute_times": [0.655547342,0.660303172], "copy_out_times": [0.660303205,0.660345437], "cpu_times": [0.655522388,0.660345437], "cpu_core": 1},
{"kernel_name": "matrix_multiply", "block_count": 1024, "thread_count": 1024, "shared_memory": 0, "kernel_launch_times": [0.655547372, 0.655549760, 0.660303120], "block_times": []},
{"copy_in_times": [0.660352078,0.660376165], "execute_times": [0.660376193,0.665128957], "copy_out_times": [0.665129003,0.665172782], "cpu_times": [0.660352078,0.665172782], "cpu_core": 1},
{"kernel_name": "matrix_multiply", "block_count": 1024, "thread_count": 1024, "shared_memory": 0, "kernel_launch_times": [0.660376224, 0.660378815, 0.665128887], "block_times": []},
{"copy_in_times": [0.665180042,0.665204808], "execute_times": [0.665204837,0.669963842], "copy_out_times": [0.669963895,0.670007786], "cpu_times": [0.665180042,0.670007786], "cpu_core": 1},
{"kernel_name": "matrix_multiply", "block_count": 1024, "thread_count": 1024, "shared_memory": 0, "kernel_launch_times": [0.665204871, 0.665207572, 0.669963780], "block_times": []},
{"copy_in_times": [0.670014593,0.670039865], "execute_times": [0.670039898,0.674808419], "copy_out_times": [0.674808453,0.674853613], "cpu_times": [0.670014593,0.674853613], "cpu_core": 1},
{"kernel_name": "matrix_multiply", "block_count": 1024, "thread_count": 1024, "shared_memory": 0, "kernel_launch_times": [0.670039927, 0.670042847, 0.674808345], "block_times": []},
{"copy_in_times": [0.674863946,0.674888041], "execute_times": [0.674888069,0.679651363], "copy_out_times": [0.679651412,0.679698748], "cpu_times": [0.674863946,0.679698748], "cpu_core": 1},
{"kernel_name": "matrix_multiply", "block_count": 1024, "thread_count": 1024, "shared_memory": 0, "kernel_launch_times": [0.674888114, 0.674890789, 0.679651297], "block_times": []},
{"copy_in_times": [0.679705753,0.679729445], "execute_times": [0.679729474,0.684489931], "copy_out_times": [0.684489979,0.684534768], "cpu_times": [0.679705753,0.684534768], "cpu_core": 1},
{"kernel_name": "matrix_multiply", "block_count": 1024, "thread_count": 1024, "shared_memory": 0, "kernel_launch_times": [0.679729508, 0.679732313, 0.684489856], "block_times": []},
{"copy_in_times": [0.684542114,0.684576931], "execute_times": [0.684576962,0.689356703], "copy_out_times": [0.689356750,0.689398439], "cpu_times": [0.684542114,0.689398439], "cpu_core": 1},
{"kernel_name": "matrix_multiply", "block_count": 1024, "thread_count": 1024, "shared_memory": 0, "kernel_launch_times": [0.684576997, 0.684579625, 0.689356631], "block_times": []},
{"copy_in_times": [0.689405858,0.689431275], "execute_times": [0.689431308,0.694203357], "copy_out_times": [0.694203396,0.694245587], "cpu_times": [0.689405858,0.694245587], "cpu_core": 1},
{"kernel_name": "matrix_multiply", "block_count": 1024, "thread_count": 1024, "shared_memory": 0, "kernel_launch_times": [0.689431335, 0.689434021, 0.694203294], "block_times": []},
{"copy_in_times": [0.694252243,0.694277073], "execute_times": [0.694277102,0.699031133], "copy_out_times": [0.699031180,0.699074079], "cpu_times": [0.694252243,0.699074079], "cpu_core": 1},
{"kernel_name": "matrix_multiply", "block_count": 1024, "thread_count": 1024, "shared_memory": 0, "kernel_launch_times": [0.694277140, 0.694279771, 0.699031071], "block_times": []},
{"copy_in_times": [0.699080757,0.699105154], "execute_times": [0.699105183,0.703880248], "copy_out_times": [0.703880286,0.703933849], "cpu_times": [0.699080757,0.703933849], "cpu_core": 1},
{"kernel_name": "matrix_multiply", "block_count": 1024, "thread_count": 1024, "shared_memory": 0, "kernel_launch_times": [0.699105215, 0.699107832, 0.703880183], "block_times": []},
{"copy_in_times": [0.703941012,0.703964691], "execute_times": [0.703964721,0.708724099], "copy_out_times": [0.708724146,0.708766973], "cpu_times": [0.703941012,0.708766973], "cpu_core": 1},
{"kernel_name": "matrix_multiply", "block_count": 1024, "thread_count": 1024, "shared_memory": 0, "kernel_launch_times": [0.703964762, 0.703967453, 0.708724046], "block_times": []},
{"copy_in_times": [0.708773704,0.708799549], "execute_times": [0.708799579,0.713594378], "copy_out_times": [0.713594418,0.713638737], "cpu_times": [0.708773704,0.713638737], "cpu_core": 1},
{"kernel_name": "matrix_multiply", "block_count": 1024, "thread_count": 1024, "shared_memory": 0, "kernel_launch_times": [0.708799610, 0.708802400, 0.713594309], "block_times": []},
{"copy_in_times": [0.713646027,0.713670904], "execute_times": [0.713670932,0.718455448], "copy_out_times": [0.718455487,0.718497216], "cpu_times": [0.713646027,0.718497216], "cpu_core": 1},
{"kernel_name": "matrix_multiply", "block_count": 1024, "thread_count": 1024, "shared_memory": 0, "kernel_launch_times": [0.713670964, 0.713674030, 0.718455385], "block_times": []},
{"copy_in_times": [0.718503793,0.718529131], "execute_times": [0.718529159,0.723308474], "copy_out_times": [0.723308508,0.723352250], "cpu_times": [0.718503793,0.723352250], "cpu_core": 1},
{"kernel_name": "matrix_multiply", "block_count": 1024, "thread_count": 1024, "shared_memory": 0, "kernel_launch_times": [0.718529191, 0.718531648, 0.723308403], "block_times": []},
{"copy_in_times": [0.723359285,0.723383499], "execute_times": [0.723383530,0.728137629], "copy_out_times": [0.728137669,0.728181268], "cpu_times": [0.723359285,0.728181268], "cpu_core": 1},
{"kernel_name": "matrix_multiply", "block_count": 1024, "thread_count": 1024, "shared_memory": 0, "kernel_launch_times": [0.723383561, 0.723386227, 0.728137576], "block_times": []},
{"copy_in_times": [0.728191367,0.728215995], "execute_times": [0.728216026,0.732991468], "copy_out_times": [0.732991521,0.733035051], "cpu_times": [0.728191367,0.733035051], "cpu_core": 1},
{"kernel_name": "matrix_multiply", "block_count": 1024, "thread_count": 1024, "shared_memory": 0, "kernel_launch_times": [0.728216061, 0.728218917, 0.732991413], "block_times": []},
{"copy_in_times": [0.733042484,0.733068149], "execute_times": [0.733068179,0.737853186], "copy_out_times": [0.737853237,0.737933065], "cpu_times": [0.733042484,0.737933065], "cpu_core": 1},
{"kernel_name": "matrix_multiply", "block_count": 1024, "thread_count": 1024, "shared_memory": 0, "kernel_launch_times": [0.733068209, 0.733070919, 0.737853133], "block_times": []},
{"copy_in_times": [0.737939656,0.737964746], "execute_times": [0.737964776,0.742725756], "copy_out_times": [0.742725802,0.742767930], "cpu_times": [0.737939656,0.742767930], "cpu_core": 1},
{"kernel_name": "matrix_multiply", "block_count": 1024, "thread_count": 1024, "shared_memory": 0, "kernel_launch_times": [0.737964806, 0.737967560, 0.742725700], "block_times": []},
{"copy_in_times": [0.742775200,0.742800368], "execute_times": [0.742800398,0.747568143], "copy_out_times": [0.747568189,0.747610077], "cpu_times": [0.742775200,0.747610077], "cpu_core": 1},
{"kernel_name": "matrix_multiply", "block_count": 1024, "thread_count": 1024, "shared_memory": 0, "kernel_launch_times": [0.742800428, 0.742803400, 0.747568089], "block_times": []},
{"copy_in_times": [0.747616895,0.747641996], "execute_times": [0.747642023,0.752391922], "copy_out_times": [0.752391975,0.752433685], "cpu_times": [0.747616895,0.752433685], "cpu_core": 1},
{"kernel_name": "matrix_multiply", "block_count": 1024, "thread_count": 1024, "shared_memory": 0, "kernel_launch_times": [0.747642055, 0.747644810, 0.752391870], "block_times": []},
{"copy_in_times": [0.752440731,0.752466923], "execute_times": [0.752466952,0.757247739], "copy_out_times": [0.757247793,0.757326994], "cpu_times": [0.752440731,0.757326994], "cpu_core": 1},
{"kernel_name": "matrix_multiply", "block_count": 1024, "thread_count": 1024, "shared_memory": 0, "kernel_launch_times": [0.752466983, 0.752469774, 0.757247686], "block_times": []},
{"copy_in_times": [0.757333756,0.757358187], "execute_times": [0.757358218,0.762124822], "copy_out_times": [0.762124875,0.762167380], "cpu_times": [0.757333756,0.762167380], "cpu_core": 1},
{"kernel_name": "matrix_multiply", "block_count": 1024, "thread_count": 1024, "shared_memory": 0, "kernel_launch_times": [0.757358250, 0.757361024, 0.762124769], "block_times": []},
{"copy_in_times": [0.762174427,0.762200121], "execute_times": [0.762200151,0.766959074], "copy_out_times": [0.766959121,0.767001223], "cpu_times": [0.762174427,0.767001223], "cpu_core": 1},
{"kernel_name": "matrix_multiply", "block_count": 1024, "thread_count": 1024, "shared_memory": 0, "kernel_launch_times": [0.762200181, 0.762203054, 0.766959022], "block_times": []},
{"copy_in_times": [0.767007869,0.767032796], "execute_times": [0.767032826,0.771851558], "copy_out_times": [0.771851594,0.771932876], "cpu_times": [0.767007869,0.771932876], "cpu_core": 1},
{"kernel_name": "matrix_multiply", "block_count": 1024, "thread_count": 1024, "shared_memory": 0, "kernel_launch_times": [0.767032858, 0.767035565, 0.771851507], "block_times": []},
{"copy_in_times": [0.771939426,0.771964078], "execute_times": [0.771964108,0.776750491], "copy_out_times": [0.776750542,0.776827727], "cpu_times": [0.771939426,0.776827727], "cpu_core": 1},
{"kernel_name": "matrix_multiply", "block_count": 1024, "thread_count": 1024, "shared_memory": 0, "kernel_launch_times": [0.771964139, 0.771966642, 0.776750438], "block_times": []},
{"copy_in_times": [0.776834775,0.776859718], "execute_times": [0.776859748,0.781620145], "copy_out_times": [0.781620194,0.781661636], "cpu_times": [0.776834775,0.781661636], "cpu_core": 1},
{"kernel_name": "matrix_multiply", "block_count": 1024, "thread_count": 1024, "shared_memory": 0, "kernel_launch_times": [0.776859778, 0.776862695, 0.781620094], "block_times": []},
{"copy_in_times": [0.781671517,0.781695015], "execute_times": [0.781695050,0.786466504], "copy_out_times": [0.786466539,0.786506447], "cpu_times": [0.781671517,0.786506447], "cpu_core": 1},
{"kernel_name": "matrix_multiply", "block_count": 1024, "thread_count": 1024, "shared_memory": 0, "kernel_launch_times": [0.781695080, 0.781697996, 0.786466451], "block_times": []},
{"copy_in_times": [0.786513922,0.786537945], "execute_times": [0.786537976,0.791319213], "copy_out_times": [0.791319262,0.791361001], "cpu_times": [0.786513922,0.791361001], "cpu_core": 1},
{"kernel_name": "matrix_multiply", "block_count": 1024, "thread_count": 1024, "shared_memory": 0, "kernel_launch_times": [0.786538006, 0.786540873, 0.791319162], "block_times": []},
{"copy_in_times": [0.791367690,0.791393998], "execute_times": [0.791394027,0.796134493], "copy_out_times": [0.796134542,0.796177593], "cpu_times": [0.791367690,0.796177593], "cpu_core": 1},
{"kernel_name": "matrix_multiply", "block_count": 1024, "thread_count": 1024, "shared_memory": 0, "kernel_launch_times": [0.791394058, 0.791396654, 0.796134402], "block_times": []},
{"copy_in_times": [0.796187192,0.796212591], "execute_times": [0.796212624,0.801005106], "copy_out_times": [0.801005153,0.801048822], "cpu_times": [0.796187192,0.801048822], "cpu_core": 1},
{"kernel_name": "matrix_multiply", "block_count": 1024, "thread_count": 1024, "shared_memory": 0, "kernel_launch_times": [0.796212673, 0.796216235, 0.801005029], "block_times": []},
{"copy_in_times": [0.801056351,0.801080942], "execute_times": [0.801080972,0.805880888], "copy_out_times": [0.805880941,0.805922434], "cpu_times": [0.801056351,0.805922434], "cpu_core": 1},
{"kernel_name": "matrix_multiply", "block_count": 1024, "thread_count": 1024, "shared_memory": 0, "kernel_launch_times": [0.801081002, 0.801083851, 0.805880825], "block_times": []},
{"copy_in_times": [0.805929472,0.805953577], "execute_times": [0.805953607,0.810722593], "copy_out_times": [0.810722639,0.810766767], "cpu_times": [0.805929472,0.810766767], "cpu_core": 1},
{"kernel_name": "matrix_multiply", "block_count": 1024, "thread_count": 1024, "shared_memory": 0, "kernel_launch_times": [0.805953643, 0.805956532, 0.810722531], "block_times": []},
{"copy_in_times": [0.810774122,0.810798672], "execute_times": [0.810798701,0.815554518], "copy_out_times": [0.815554564,0.815594742], "cpu_times": [0.810774122,0.815594742], "cpu_core": 1},
{"kernel_name": "matrix_multiply", "block_count": 1024, "thread_count": 1024, "shared_memory": 0, "kernel_launch_times": [0.810798732, 0.810801381, 0.815554454], "block_times": []},
{"copy_in_times": [0.815601416,0.815625242], "execute_times": [0.815625272,0.820349604], "copy_out_times": [0.820349653,0.820391623], "cpu_times": [0.815601416,0.820391623], "cpu_core": 1},
{"kernel_name": "matrix_multiply", "block_count": 1024, "thread_count": 1024, "shared_memory": 0, "kernel_launch_times": [0.815625302, 0.815627893, 0.820349550], "block_times": []},
{"copy_in_times": [0.820398202,0.820422731], "execute_times": [0.820422762,0.825172663], "copy_out_times": [0.825172710,0.825215150], "cpu_times": [0.820398202,0.825215150], "cpu_core": 1},
{"kernel_name": "matrix_multiply", "block_count": 1024, "thread_count": 1024, "shared_memory": 0, "kernel_launch_times": [0.820422792, 0.820425646, 0.825172607], "block_times": []},
{"copy_in_times": [0.825222254,0.825246217], "execute_times": [0.825246247,0.830016804], "copy_out_times": [0.830016858,0.830060520], "cpu_times": [0.825222254,0.830060520], "cpu_core": 1},
{"kernel_name": "matrix_multiply", "block_count": 1024, "thread_count": 1024, "shared_memory": 0, "kernel_launch_times": [0.825246277, 0.825248852, 0.830016740], "block_times": []},
{"copy_in_times": [0.830067273,0.830091393], "execute_times": [0.830091423,0.834909377], "copy_out_times": [0.834909423,0.834951865], "cpu_times": [0.830067273,0.834951865], "cpu_core": 1},
{"kernel_name": "matrix_multiply", "block_count": 1024, "thread_count": 1024, "shared_memory": 0, "kernel_launch_times": [0.830091453, 0.830094302, 0.834909313], "block_times": []},
{"copy_in_times": [0.834962965,0.834988241], "execute_times": [0.834988269,0.839783841], "copy_out_times": [0.839783885,0.839828494], "cpu_times": [0.834962965,0.839828494], "cpu_core": 1},
{"kernel_name": "matrix_multiply", "block_count": 1024, "thread_count": 1024, "shared_memory": 0, "kernel_launch_times": [0.834988309, 0.834990973, 0.839783788], "block_times": []},
{"copy_in_times": [0.839835538,0.839861286], "execute_times": [0.839861316,0.844629698], "copy_out_times": [0.844629750,0.844672383], "cpu_times": [0.839835538,0.844672383], "cpu_core": 1},
{"kernel_name": "matrix_multiply", "block_count": 1024, "thread_count": 1024, "shared_memory": 0, "kernel_launch_times": [0.839861345, 0.839864289, 0.844629644], "block_times": []},
{"copy_in_times": [0.844678936,0.844703420], "execute_times": [0.844703449,0.849487827], "copy_out_times": [0.849487880,0.849531447], "cpu_times": [0.844678936,0.849531447], "cpu_core": 1},
{"kernel_name": "matrix_multiply", "block_count": 1024, "thread_count": 1024, "shared_memory": 0, "kernel_launch_times": [0.844703477, 0.844706076, 0.849487760], "block_times": []},
{"copy_in_times": [0.849538661,0.849563809], "execute_times": [0.849563838,0.854299322], "copy_out_times": [0.854299368,0.854342726], "cpu_times": [0.849538661,0.854342726], "cpu_core": 1},
{"kernel_name": "matrix_multiply", "block_count": 1024, "thread_count": 1024, "shared_memory": 0, "kernel_launch_times": [0.849563869, 0.849566592, 0.854299270], "block_times": []},
{"copy_in_times": [0.854349395,0.854376025], "execute_times": [0.854376055,0.859172220], "copy_out_times": [0.859172273,0.859214503], "cpu_times": [0.854349395,0.859214503], "cpu_core": 1},
{"kernel_name": "matrix_multiply", "block_count": 1024, "thread_count": 1024, "shared_memory": 0, "kernel_launch_times": [0.854376084, 0.854378641, 0.859172169], "block_times": []},
{"copy_in_times": [0.859221609,0.859246663], "execute_times": [0.859246692,0.863999837], "copy_out_times": [0.863999889,0.864042561], "cpu_times": [0.859221609,0.864042561], "cpu_core": 1},
{"kernel_name": "matrix_multiply", "block_count": 1024, "thread_count": 1024, "shared_memory": 0, "kernel_launch_times": [0.859246723, 0.859249840, 0.863999774], "block_times": []},
{"copy_in_times": [0.864049458,0.864073925], "execute_times": [0.864073956,0.868837041], "copy_out_times": [0.868837087,0.868883075], "cpu_times": [0.864049458,0.868883075], "cpu_core": 1},
{"kernel_name": "matrix_multiply", "block_count": 1024, "thread_count": 1024, "shared_memory": 0, "kernel_launch_times": [0.864073985, 0.864076713, 0.868836976], "block_times": []},
{"copy_in_times": [0.868890209,0.868915069], "execute_times": [0.868915099,0.873704557], "copy_out_times": [0.873704613,0.873749636], "cpu_times": [0.868890209,0.873749636], "cpu_core": 1},
{"kernel_name": "matrix_multiply", "block_count": 1024, "thread_count": 1024, "shared_memory": 0, "kernel_launch_times": [0.868915127, 0.868917855, 0.873704500], "block_times": []},
{"copy_in_times": [0.873757137,0.873782006], "execute_times": [0.873782033,0.878556860], "copy_out_times": [0.878556908,0.878599427], "cpu_times": [0.873757137,0.878599427], "cpu_core": 1},
{"kernel_name": "matrix_multiply", "block_count": 1024, "thread_count": 1024, "shared_memory": 0, "kernel_launch_times": [0.873782065, 0.873784910, 0.878556796], "block_times": []},
{"copy_in_times": [0.878606592,0.878630677], "execute_times": [0.878630706,0.883390746], "copy_out_times": [0.883390795,0.883434969], "cpu_times": [0.878606592,0.883434969], "cpu_core": 1},
{"kernel_name": "matrix_multiply", "block_count": 1024, "thread_count": 1024, "shared_memory": 0, "kernel_launch_times": [0.878630736, 0.878633399, 0.883390691], "block_times": []},
{"copy_in_times": [0.883441573,0.883466403], "execute_times": [0.883466432,0.888253018], "copy_out_times": [0.888253066,0.888295280], "cpu_times": [0.883441573,0.888295280], "cpu_core": 1},
{"kernel_name": "matrix_multiply", "block_count": 1024, "thread_count": 1024, "shared_memory": 0, "kernel_launch_times": [0.883466463, 0.883469134, 0.888252955], "block_times": []},
{"copy_in_times": [0.888305393,0.888329975], "execute_times": [0.888330004,0.893088834], "copy_out_times": [0.893088880,0.893132606], "cpu_times": [0.888305393,0.893132606], "cpu_core": 1},
{"kernel_name": "matrix_multiply", "block_count": 1024, "thread_count": 1024, "shared_memory": 0, "kernel_launch_times": [0.888330038, 0.888332972, 0.893088780], "block_times": []},
{"copy_in_times": [0.893140316,0.893165679], "execute_times": [0.893165709,0.897894593], "copy_out_times": [0.897894640,0.897938208], "cpu_times": [0.893140316,0.897938208], "cpu_core": 1},
{"kernel_name": "matrix_multiply", "block_count": 1024, "thread_count": 1024, "shared_memory": 0, "kernel_launch_times": [0.893165739, 0.893168801, 0.897894515], "block_times": []},
{"copy_in_times": [0.897945531,0.897970213], "execute_times": [0.897970243,0.902752420], "copy_out_times": [0.902752467,0.902825175], "cpu_times": [0.897945531,0.902825175], "cpu_core": 1},
{"kernel_name": "matrix_multiply", "block_count": 1024, "thread_count": 1024, "shared_memory": 0, "kernel_launch_times": [0.897970273, 0.897973171, 0.902752354], "block_times": []},
{"copy_in_times": [0.902832392,0.902857769], "execute_times": [0.902857798,0.907664286], "copy_out_times": [0.907664333,0.907710813], "cpu_times": [0.902832392,0.907710813], "cpu_core": 1},
{"kernel_name": "matrix_multiply", "block_count": 1024, "thread_count": 1024, "shared_memory": 0, "kernel_launch_times": [0.902857828, 0.902860674, 0.907664220], "block_times": []},
{"copy_in_times": [0.907717481,0.907741872], "execute_times": [0.907741901,0.912516806], "copy_out_times": [0.912516860,0.912559258], "cpu_times": [0.907717481,0.912559258], "cpu_core": 1},
{"kernel_name": "matrix_multiply", "block_count": 1024, "thread_count": 1024, "shared_memory": 0, "kernel_launch_times": [0.907741932, 0.907744587, 0.912516743], "block_times": []},
{"copy_in_times": [0.912565932,0.912590246], "execute_times": [0.912590275,0.917362411], "copy_out_times": [0.917362458,0.917403298], "cpu_times": [0.912565932,0.917403298], "cpu_core": 1},
{"kernel_name": "matrix_multiply", "block_count": 1024, "thread_count": 1024, "shared_memory": 0, "kernel_launch_times": [0.912590309, 0.912593023, 0.917362344], "block_times": []},
{"copy_in_times": [0.917410631,0.917435213], "execute_times": [0.917435245,0.922175779], "copy_out_times": [0.922175827,0.922219416], "cpu_times": [0.917410631,0.922219416], "cpu_core": 1},
{"kernel_name": "matrix_multiply", "block_count": 1024, "thread_count": 1024, "shared_memory": 0, "kernel_launch_times": [0.917435274, 0.917438187, 0.922175715], "block_times": []},
{"copy_in_times": [0.922226733,0.922251115], "execute_times": [0.922251143,0.927023172], "copy_out_times": [0.927023215,0.927066343], "cpu_times": [0.922226733,0.927066343], "cpu_core": 1},
{"kernel_name": "matrix_multiply", "block_count": 1024, "thread_count": 1024, "shared_memory": 0, "kernel_launch_times": [0.922251174, 0.922253914, 0.927023108], "block_times": []},
{"copy_in_times": [0.927073084,0.927097308], "execute_times": [0.927097338,0.931869953], "copy_out_times": [0.931869999,0.931925956], "cpu_times": [0.927073084,0.931925956], "cpu_core": 1},
{"kernel_name": "matrix_multiply", "block_count": 1024, "thread_count": 1024, "shared_memory": 0, "kernel_launch_times": [0.927097370, 0.927099955, 0.931869899], "block_times": []},
{"copy_in_times": [0.931932559,0.931957920], "execute_times": [0.931957953,0.936740279], "copy_out_times": [0.936740318,0.936784471], "cpu_times": [0.931932559,0.936784471], "cpu_core": 1},
{"kernel_name": "matrix_multiply", "block_count": 1024, "thread_count": 1024, "shared_memory": 0, "kernel_launch_times": [0.931957982, 0.931960395, 0.936740215], "block_times": []},
{"copy_in_times": [0.936791522,0.936816705], "execute_times": [0.936816734,0.941558128], "copy_out_times": [0.941558175,0.941601200], "cpu_times": [0.936791522,0.941601200], "cpu_core": 1},
{"kernel_name": "matrix_multiply", "block_count": 1024, "thread_count": 1024, "shared_memory": 0, "kernel_launch_times": [0.936816764, 0.936819415, 0.941558074], "block_times": []},
{"copy_in_times": [0.941611310,0.941636048], "execute_times": [0.941636076,0.946445457], "copy_out_times": [0.946445503,0.946486518], "cpu_times": [0.941611310,0.946486518], "cpu_core": 1},
{"kernel_name": "matrix_multiply", "block_count": 1024, "thread_count": 1024, "shared_memory": 0, "kernel_launch_times": [0.941636115, 0.941638887, 0.946445393], "block_times": []}
]}